podaac/__init__.py
podaac/drive.py
podaac/l2ss.py
podaac/mcc.py
podaac/oceancolor.py
podaac/podaac.py
podaac/podaac_utils.py
podaac/tests/__init__.py
podaac/tests/drive_test.py
podaac/tests/l2ss_tests.py
podaac/tests/mcc_test.py
podaac/tests/oceancolor_test.py
podaac/tests/podaac_test.py
podaacpy-2.4.0.dist-info/LICENSE
podaacpy-2.4.0.dist-info/METADATA
podaacpy-2.4.0.dist-info/WHEEL
podaacpy-2.4.0.dist-info/namespace_packages.txt
podaacpy-2.4.0.dist-info/top_level.txt
podaacpy-2.4.0.dist-info/RECORD
