Metadata-Version: 2.1
Name: podaacpy
Version: 2.4.0
Summary: PO.DAAC Python API
Home-page: https://github.com/nasa/podaacpy
Author: Lewis John McGibbney
Author-email: lewis.j.mcgibbney@jpl.nasa.gov
License: Apache License, Version 2.0
Download-URL: http://pypi.python.org/pypi/podaacpy/
Keywords: dataset,granule,compliance,nasa,jpl,podaac
Platform: UNKNOWN
Classifier: Environment :: Console
Classifier: Intended Audience :: Developers
Classifier: Intended Audience :: Information Technology
Classifier: Intended Audience :: Science/Research
Classifier: Topic :: Scientific/Engineering
Classifier: Development Status :: 5 - Production/Stable
Classifier: License :: OSI Approved :: Apache Software License
Classifier: Operating System :: OS Independent
Classifier: Programming Language :: Python
Classifier: Topic :: Internet :: WWW/HTTP
Classifier: Topic :: Software Development :: Libraries :: Python Modules
Requires-Dist: beautifulsoup4
Requires-Dist: configparser
Requires-Dist: defusedxml
Requires-Dist: future
Requires-Dist: pathlib2
Requires-Dist: requests
